genice2_cif/__init__.py
genice2_cif/lattices/__init__.py
genice2_cif/lattices/cif.py
genice2_cif/lattices/zeolite.py
genice2_cif-2.2.1.dist-info/METADATA
genice2_cif-2.2.1.dist-info/WHEEL
genice2_cif-2.2.1.dist-info/entry_points.txt
genice2_cif-2.2.1.dist-info/RECORD
