Metadata-Version: 2.1
Name: genice2-cif
Version: 2.2.1
Summary: CIF reader plugin for GenIce2.
License: MIT
Author: vitroid
Author-email: vitroid@gmail.com
Requires-Python: >=3.9,<4.0
Classifier: License :: OSI Approved :: MIT License
Classifier: Programming Language :: Python :: 3
Classifier: Programming Language :: Python :: 3.9
Classifier: Programming Language :: Python :: 3.10
Classifier: Programming Language :: Python :: 3.11
Classifier: Programming Language :: Python :: 3.12
Requires-Dist: GenIce2 (>=2.2.5.2,<3.0.0.0)
Requires-Dist: cif2ice (>=0.3.0)
Requires-Dist: validators
